pyobsplot/__init__.py
pyobsplot/data.py
pyobsplot/js_modules.py
pyobsplot/jsdom.py
pyobsplot/obsplot.py
pyobsplot/parsing.py
pyobsplot/plot.py
pyobsplot/utils.py
pyobsplot/widget.py
pyobsplot/static/static-styles.css
pyobsplot/static/static-widget.js
pyobsplot/static/template.typ
pyobsplot-0.5.4.dist-info/METADATA
pyobsplot-0.5.4.dist-info/WHEEL
pyobsplot-0.5.4.dist-info/licenses/LICENSE
pyobsplot-0.5.4.dist-info/RECORD
