Metadata-Version: 2.4
Name: pyobsplot
Version: 0.5.4
Summary: Observable Plot in Jupyter notebooks and Quarto documents
Project-URL: homepage, https://github.com/juba/pyobsplot
Project-URL: documentation, https://juba.github.io/pyobsplot
Project-URL: repository, https://github.com/juba/pyobsplot
Project-URL: changelog, https://github.com/juba/pyobsplot/blob/main/NEWS.md
Author-email: Julien Barnier <julien@nozav.org>
License: MIT License
License-File: LICENSE
Classifier: Development Status :: 4 - Beta
Classifier: Framework :: Jupyter :: JupyterLab
Classifier: License :: OSI Approved :: MIT License
Classifier: Programming Language :: JavaScript
Classifier: Programming Language :: Python :: 3
Classifier: Topic :: Scientific/Engineering :: Visualization
Requires-Python: >=3.10
Requires-Dist: anywidget>=0.9.18
Requires-Dist: pandas>=2.0.0
Requires-Dist: polars>=1.4.1
Requires-Dist: pyarrow>=20.0.0
Requires-Dist: requests
Provides-Extra: typst
Requires-Dist: typst>=0.13.2; extra == 'typst'
